djangorave/__init__.py
djangorave/admin.py
djangorave/apps.py
djangorave/migrations/0001_initial.py
djangorave/migrations/0002_auto_20190815_0524.py
djangorave/migrations/__init__.py
djangorave/models.py
djangorave/serializers.py
djangorave/settings.py
djangorave/static/djangorave/js/payment.js
djangorave/templates/djangorave/pay_button.html
djangorave/templates/djangorave/transaction.html
djangorave/templatetags/__init__.py
djangorave/templatetags/djangorave_tags.py
djangorave/tests/__init__.py
djangorave/tests/factories.py
djangorave/tests/test_serializers.py
djangorave/tests/test_template_tags.py
djangorave/tests/test_utils.py
djangorave/tests/test_views.py
djangorave/urls.py
djangorave/utils.py
djangorave/views.py
djangorave-0.1.1.dist-info/LICENSE
djangorave-0.1.1.dist-info/WHEEL
djangorave-0.1.1.dist-info/METADATA
djangorave-0.1.1.dist-info/RECORD
