Metadata-Version: 2.1
Name: djangorave
Version: 0.1.1
Summary: Django integration for Flutterwave Rave Card payments and subscriptions
Home-page: https://github.com/bdelate/django-rave.git
License: MIT
Keywords: flutterwave,rave,django
Author: Brendon Delate
Author-email: brendon.delate@gmail.com
Requires-Python: >=3.6,<4
Classifier: Development Status :: 1 - Planning
Classifier: Environment :: Web Environment
Classifier: Framework :: Django
Classifier: Framework :: Django :: 2.2
Classifier: Intended Audience :: Developers
Classifier: License :: OSI Approved :: MIT License
Classifier: Operating System :: OS Independent
Classifier: Programming Language :: Python :: 3
Classifier: Programming Language :: Python :: 3.6
Classifier: Programming Language :: Python :: 3.7
Classifier: Topic :: Software Development :: Libraries
Classifier: Topic :: Utilities
Requires-Dist: django (>=2.2,<3.0)
Requires-Dist: djangorestframework (>=3.10,<4.0)
Requires-Dist: requests (>=2.22,<3.0)
Project-URL: Repository, https://github.com/bdelate/django-rave.git
